opower/__init__.py
opower/__main__.py
opower/const.py
opower/exceptions.py
opower/helpers.py
opower/opower.py
opower/py.typed
opower/utilities/__init__.py
opower/utilities/aepbase.py
opower/utilities/aepohio.py
opower/utilities/aeptexas.py
opower/utilities/appalachianpower.py
opower/utilities/atlanticcityelectric.py
opower/utilities/base.py
opower/utilities/bge.py
opower/utilities/burbankwaterandpower.py
opower/utilities/coautilities.py
opower/utilities/comed.py
opower/utilities/coned.py
opower/utilities/delmarva.py
opower/utilities/duquesnelight.py
opower/utilities/evergy.py
opower/utilities/eversource.py
opower/utilities/exelon.py
opower/utilities/glendalewaterandpower.py
opower/utilities/helpers.py
opower/utilities/indianamichiganpower.py
opower/utilities/kentuckypower.py
opower/utilities/nationalgrid.py
opower/utilities/nationalgridli.py
opower/utilities/nationalgridma.py
opower/utilities/nationalgridnymetro.py
opower/utilities/nationalgridnyupstate.py
opower/utilities/oidchelper.py
opower/utilities/oru.py
opower/utilities/peco.py
opower/utilities/pepco.py
opower/utilities/pge.py
opower/utilities/portlandgeneral.py
opower/utilities/pse.py
opower/utilities/psoklahoma.py
opower/utilities/scl.py
opower/utilities/smeco.py
opower/utilities/smud.py
opower/utilities/swepco.py
opower/utilities/swgas.py
opower-0.17.0.dist-info/licenses/LICENSE
opower-0.17.0.dist-info/METADATA
opower-0.17.0.dist-info/WHEEL
opower-0.17.0.dist-info/top_level.txt
opower-0.17.0.dist-info/RECORD
