Metadata-Version: 2.4
Name: opower
Version: 0.17.0
Summary: A Python library for getting historical and forecasted usage/cost from utilities that use opower.com such as PG&E
Author-email: tronikos <tronikos@gmail.com>
License: Apache-2.0
Project-URL: Homepage, https://github.com/tronikos/opower
Project-URL: Bug Tracker, https://github.com/tronikos/opower/issues
Requires-Python: >=3.11
License-File: LICENSE
Requires-Dist: aiohttp>=3.8
Requires-Dist: aiozoneinfo>=0.1
Requires-Dist: arrow>=1.2
Requires-Dist: pyotp>=2.0
Provides-Extra: test
Requires-Dist: pytest; extra == "test"
Requires-Dist: pytest-asyncio; extra == "test"
Requires-Dist: python-dotenv; extra == "test"
Dynamic: license-file
